LICENSE
README.md
setup.py
python4excel/__init__.py
python4excel/python4excel.py
python4excel.egg-info/PKG-INFO
python4excel.egg-info/SOURCES.txt
python4excel.egg-info/dependency_links.txt
python4excel.egg-info/requires.txt
python4excel.egg-info/top_level.txt