Metadata-Version: 2.1
Name: python4excel
Version: 0.0.1
Summary: python for excel
Home-page: https://gitee.com/CoderWanFeng/python4excel
Author: 程序员晚枫
Author-email: 1957875073@qq.com
License: MIT Licence
Keywords: pip,python4excel
Platform: any
Requires-Python: >=3.6
License-File: LICENSE
